wikiarticle/__init__.py
wikiarticle/wikiarticle.py
wikiarticle/models/__init__.py
wikiarticle/models/text_type.py
wikiarticle/models/utils.py
wikiarticle/models/wiki_image.py
wikiarticle/models/wiki_quote.py
wikiarticle/models/wiki_text.py
wikiarticle-0.0.2.dist-info/METADATA
wikiarticle-0.0.2.dist-info/WHEEL
wikiarticle-0.0.2.dist-info/top_level.txt
wikiarticle-0.0.2.dist-info/RECORD
