Metadata-Version: 2.1
Name: wikiarticle
Version: 0.0.2
Summary: wikipedia atricles in an object oriented format
Home-page: https://github.com/kkristof200/py_wikiarticle
Author: Kristof
License: UNKNOWN
Platform: UNKNOWN
Classifier: Programming Language :: Python :: 3
Classifier: License :: OSI Approved :: MIT License
Classifier: Operating System :: OS Independent
Requires-Python: >=3.5
Requires-Dist: beautifulsoup4
Requires-Dist: kcu
